{
  "project_info": {
    "project_number": "613169869033",
    "project_id": "chatapp-5e192",
    "storage_bucket": "chatapp-5e192.appspot.com"
  },
  "client": [
    {
      "client_info": {
        "mobilesdk_app_id": "1:613169869033:android:824c954171b46a89210078",
        "android_client_info": {
          "package_name": "com.example.chat_app"
        }
      },
      "oauth_client": [],
      "api_key": [
        {
          "current_key": "AIzaSyATTZ5qMiDMpjTkLFbhD1dq1Js40mKxoV0"
        }
      ],
      "services": {
        "appinvite_service": {
          "other_platform_oauth_client": []
        }
      }
    }
  ],
  "configuration_version": "1"
}